markdown_html_pdf/__init__.py
markdown_html_pdf/cli.py
markdown_html_pdf/py.typed
markdown_html_pdf/_constants/api_keys.py
markdown_html_pdf/_constants/paths.py
markdown_html_pdf/_docs/__init__.py
markdown_html_pdf/_docs/html/example.html
markdown_html_pdf/_docs/html/template.html
markdown_html_pdf/_docs/markdown/AWS Automotive Solutions Map.md
markdown_html_pdf/_docs/markdown/IA na indústria de fertilizantes.md
markdown_html_pdf/_docs/markdown/example.md
markdown_html_pdf/_docs/markdown/extract_for_rag_prompt.md
markdown_html_pdf/_docs/pdf/AWS Automotive Solutions Map.pdf
markdown_html_pdf/_docs/pdf/IA na indústria de fertilizantes.pdf
markdown_html_pdf/_docs/pdf/example.pdf
markdown_html_pdf/_fonts/segoeui.ttf
markdown_html_pdf/_fonts/segoeuib.ttf
markdown_html_pdf/_fonts/segoeuii.ttf
markdown_html_pdf/_fonts/segoeuil.ttf
markdown_html_pdf/_fonts/segoeuisl.ttf
markdown_html_pdf/_fonts/segoeuiz.ttf
markdown_html_pdf/_fonts/seguibl.ttf
markdown_html_pdf/_fonts/seguibli.ttf
markdown_html_pdf/_fonts/seguiemj-windows.ttf
markdown_html_pdf/_fonts/seguiemj.ttf
markdown_html_pdf/_fonts/seguihis.ttf
markdown_html_pdf/_fonts/seguili.ttf
markdown_html_pdf/_fonts/seguisb.ttf
markdown_html_pdf/_fonts/seguisbi.ttf
markdown_html_pdf/_fonts/seguisli.ttf
markdown_html_pdf/_fonts/seguisym.ttf
markdown_html_pdf/_llms/fallback_llm.py
markdown_html_pdf/_llms/fireworks.py
markdown_html_pdf/_llms/groq.py
markdown_html_pdf/_utils/generate_css.py
markdown_html_pdf/_utils/pygments.css
markdown_html_pdf/scripts/__init__.py
markdown_html_pdf/scripts/__main__.py
markdown_html_pdf/scripts/install_emoji_font.py
markdown_html_pdf/scripts/install_segoe_ui_emoji_on_linux.sh
markdown_html_pdf/tools/__init__.py
markdown_html_pdf/tools/_html_to_pdf.py
markdown_html_pdf/tools/_markdown_to_html.py
markdown_html_pdf/tools/_markdown_to_pdf.py
markdown_html_pdf/tools/_pdf_to_markdown.py
markdown_html_pdf-1.0.0.dist-info/METADATA
markdown_html_pdf-1.0.0.dist-info/WHEEL
markdown_html_pdf-1.0.0.dist-info/entry_points.txt
markdown_html_pdf-1.0.0.dist-info/licenses/LICENSE
markdown_html_pdf-1.0.0.dist-info/RECORD
