Metadata-Version: 2.4
Name: markdown-html-pdf
Version: 1.0.0
Summary: A powerful Python package to convert Markdown files to PDF with syntax highlighting and emoji support
Project-URL: Homepage, https://github.com/bellanda/markdown-html-pdf
Project-URL: Repository, https://github.com/bellanda/markdown-html-pdf
Project-URL: Issues, https://github.com/bellanda/markdown-html-pdf/issues
Author-email: Gustavo Casadei Bellanda <bellanda.dev@outlook.com>
License: MIT License
License-File: LICENSE
Keywords: converter,markdown,pdf,playwright,syntax-highlighting
Classifier: Development Status :: 4 - Beta
Classifier: Intended Audience :: Developers
Classifier: Intended Audience :: End Users/Desktop
Classifier: License :: OSI Approved :: MIT License
Classifier: Operating System :: OS Independent
Classifier: Programming Language :: Python :: 3
Classifier: Programming Language :: Python :: 3.8
Classifier: Programming Language :: Python :: 3.9
Classifier: Programming Language :: Python :: 3.10
Classifier: Programming Language :: Python :: 3.11
Classifier: Programming Language :: Python :: 3.12
Classifier: Programming Language :: Python :: 3.13
Classifier: Topic :: Documentation
Classifier: Topic :: Text Processing :: Markup
Classifier: Topic :: Utilities
Requires-Python: >=3.9
Requires-Dist: click>=8.0.0
Requires-Dist: fireworks-ai>=0.17.16
Requires-Dist: flask>=3.1.1
Requires-Dist: groq>=0.29.0
Requires-Dist: html2docx>=1.6.0
Requires-Dist: linkify-it-py>=2.0.3
Requires-Dist: markdown-it-py>=3.0.0
Requires-Dist: playwright>=1.53.0
Requires-Dist: pygments>=2.18.0
Requires-Dist: pymupdf>=1.26.1
Requires-Dist: python-dotenv>=1.1.1
Requires-Dist: requests>=2.32.4
Provides-Extra: dev
Requires-Dist: pytest-asyncio>=0.21.0; extra == 'dev'
Requires-Dist: pytest>=7.0.0; extra == 'dev'
Requires-Dist: ruff>=0.1.0; extra == 'dev'
